byecarl/__init__.py
byecarl-0.0.3.dist-info/METADATA
byecarl-0.0.3.dist-info/WHEEL
byecarl-0.0.3.dist-info/top_level.txt
byecarl-0.0.3.dist-info/RECORD
