Metadata-Version: 2.1
Name: byecarl
Version: 0.0.3
Summary: Goodbye message for Carl
Author: Jordan
Author-email: 
Keywords: python,carl,message,bye,goodbye
Classifier: Development Status :: 1 - Planning
Classifier: Intended Audience :: Developers
Classifier: Programming Language :: Python :: 3
Classifier: Operating System :: Unix
Classifier: Operating System :: MacOS :: MacOS X
Classifier: Operating System :: Microsoft :: Windows
